{
  "tags": {
    "wired-input": {
      "categories": [
        "flow content",
        "phrasing content",
        "interactive content",
        "listed content",
        "labelable",
        "submittable content",
        "resettable",
        "form-associated content",
        "palpable content"
      ],
      "allowedSubTags": [],
      "attributes": {
        "placeholder": {
          "description": "Placeholder text for the input."
        },
        "disabled": {
          "type": "boolean"
        },
        "type": {
          "description": "Input type e.g. password",
          "options": {
            "password": {},
            "text": {}
          }
        },
        "value": {
          "description": "Value of the text."
        }
      }
    }
  }
}
